{
  "id": "6hkUWV6NOaG8vLv",
  "unique_key": "https://www.tiktok.com/@yasuocine99/video/7522843830362688790",
  "order_no": null,
  "handled_at": "2025-07-04 09:44:48.722208+00:00",
  "request": {
    "url": "https://www.tiktok.com/@yasuocine99/video/7522843830362688790",
    "method": "GET",
    "headers": {},
    "payload": null,
    "user_data": {
      "__crawlee": {
        "state": 3,
        "crawlDepth": 1
      },
      "label": "video",
      "url": "https://www.tiktok.com/@yasuocine99/video/7522843830362688790"
    },
    "retry_count": 0,
    "no_retry": false,
    "loaded_url": "https://www.tiktok.com/@yasuocine99/video/7522843830362688790",
    "handled_at": "2025-07-04 09:44:48.722208+00:00",
    "unique_key": "https://www.tiktok.com/@yasuocine99/video/7522843830362688790",
    "id": "6hkUWV6NOaG8vLv"
  }
}